pytelebot/__init__.py
pytelebot-0.0.1.dist-info/LICENSE
pytelebot-0.0.1.dist-info/METADATA
pytelebot-0.0.1.dist-info/WHEEL
pytelebot-0.0.1.dist-info/top_level.txt
pytelebot-0.0.1.dist-info/RECORD
