Metadata-Version: 2.1
Name: pytelebot
Version: 0.0.1
Summary: Python Telegram bot API
Home-page: https://github.com/AlexZaharchuk/pytelebot
Author: Alex Zaharchuk
Author-email: olekmay@gmail.com
License: UNKNOWN
Platform: UNKNOWN
Classifier: Programming Language :: Python :: 3
Classifier: License :: OSI Approved :: MIT License
Classifier: Operating System :: OS Independent
Requires-Python: >=3.6
